filterpicker/__init__.py
filterpicker/filterpicker.py
filterpicker-1.1.0.data/scripts/run_filter_picker.py
filterpicker-1.1.0.dist-info/LICENSE.txt
filterpicker-1.1.0.dist-info/METADATA
filterpicker-1.1.0.dist-info/WHEEL
filterpicker-1.1.0.dist-info/top_level.txt
filterpicker-1.1.0.dist-info/RECORD
