Metadata-Version: 2.1
Name: filterpicker
Version: 1.1.0
Summary: Python implementation of the A.Lomax Filter-Picker
Home-page: https://github.com/mbagagli/filterpicker
Author: Matteo Bagagli
Author-email: matteo.bagagli@ingv.it
License: UNKNOWN
Platform: UNKNOWN
Classifier: Programming Language :: Python :: 3
Classifier: License :: OSI Approved :: MIT License
Classifier: Operating System :: Unix
Classifier: Operating System :: MacOS
Classifier: Intended Audience :: Science/Research
Requires-Python: >=3.6
Requires-Dist: numpy (>=1.14.2)
Requires-Dist: pytest (>=4.4)
Requires-Dist: matplotlib
